quantitativelib/__init__.py
quantitativelib/_utils.py
quantitativelib/base.py
quantitativelib/options.py
quantitativelib/stats.py
quantitativelib/stochastics.py
quantitativelib/volatility.py
quantitativelib-0.3.3.dist-info/licenses/LICENSE
quantitativelib-0.3.3.dist-info/METADATA
quantitativelib-0.3.3.dist-info/WHEEL
quantitativelib-0.3.3.dist-info/top_level.txt
quantitativelib-0.3.3.dist-info/RECORD
