Metadata-Version: 2.4
Name: quantitativelib
Version: 0.3.3
Summary: A stock analysis tool for quants
Author: Pheneas Newman
License: MIT
Requires-Python: >=3.8
License-File: LICENSE
Requires-Dist: yfinance
Requires-Dist: pandas
Requires-Dist: matplotlib
Requires-Dist: numpy
Requires-Dist: scipy
Requires-Dist: arch
Dynamic: license-file
